africanelephantdatabasedatadownloader/__init__.py
africanelephantdatabasedatadownloader/__main__.py
africanelephantdatabasedatadownloader/_version.py
africanelephantdatabasedatadownloader/lib/__init__.py
africanelephantdatabasedatadownloader/lib/continent.py
africanelephantdatabasedatadownloader/lib/country.py
africanelephantdatabasedatadownloader/lib/databaseobject.py
africanelephantdatabasedatadownloader/lib/databaseroot.py
africanelephantdatabasedatadownloader/lib/dictlike.py
africanelephantdatabasedatadownloader/lib/inputsystem.py
africanelephantdatabasedatadownloader/lib/region.py
africanelephantdatabasedatadownloader/lib/stratum.py
africanelephantdatabasedatadownloader/lib/year.py
africanelephantdatabasedatadownloader-0.10.dist-info/LICENSE
africanelephantdatabasedatadownloader-0.10.dist-info/METADATA
africanelephantdatabasedatadownloader-0.10.dist-info/WHEEL
africanelephantdatabasedatadownloader-0.10.dist-info/entry_points.txt
africanelephantdatabasedatadownloader-0.10.dist-info/top_level.txt
africanelephantdatabasedatadownloader-0.10.dist-info/RECORD
