Metadata-Version: 2.1
Name: africanelephantdatabasedatadownloader
Version: 0.10
Summary: Download data from the African Elephant Database
Home-page: https://gitlab.com/helics-lab/africanelephantdatabasedatadownloader
Author: Christoph Fink
Author-email: christoph.fink@helsinki.fi
License: GPLv3
Platform: UNKNOWN
Classifier: Programming Language :: Python :: 3
Classifier: License :: OSI Approved :: GNU General Public License v3 (GPLv3)
Classifier: Operating System :: OS Independent
Requires-Dist: beautifulsoup4 (>=4.7.0)
Requires-Dist: geopandas
Requires-Dist: requests
Requires-Dist: shapely
Requires-Dist: versioneer
